behaviors/__init__.py
behaviors/apps.py
behaviors/behaviors.py
behaviors/compat.py
behaviors/forms.py
behaviors/managers.py
behaviors/querysets.py
django_behaviors-0.5.1.dist-info/DESCRIPTION.rst
django_behaviors-0.5.1.dist-info/METADATA
django_behaviors-0.5.1.dist-info/RECORD
django_behaviors-0.5.1.dist-info/WHEEL
django_behaviors-0.5.1.dist-info/metadata.json
django_behaviors-0.5.1.dist-info/top_level.txt
