Metadata-Version: 2.0
Name: django-behaviors
Version: 0.5.1
Summary: Common behaviors for Django Models, e.g. Timestamps, Publishing, Authoring/Editing and more.
Home-page: https://github.com/audiolion/django-behaviors
Author: Ryan Castner
Author-email: castner.rr@gmail.com
License: MIT
Keywords: django-behaviors
Platform: UNKNOWN
Classifier: Development Status :: 4 - Beta
Classifier: Framework :: Django
Classifier: Framework :: Django :: 1.8
Classifier: Framework :: Django :: 1.11
Classifier: Framework :: Django :: 2.0
Classifier: Intended Audience :: Developers
Classifier: License :: OSI Approved :: BSD License
Classifier: Natural Language :: English
Classifier: Programming Language :: Python :: 2
Classifier: Programming Language :: Python :: 2.7
Classifier: Programming Language :: Python :: 3
Classifier: Programming Language :: Python :: 3.4
Classifier: Programming Language :: Python :: 3.5
Classifier: Programming Language :: Python :: 3.6
